spotifio/__init__.py
spotifio/client.py
spotifio/oauth.py
spotifio/storage.py
spotifio-0.1.6.dist-info/licenses/LICENSE
spotifio-0.1.6.dist-info/METADATA
spotifio-0.1.6.dist-info/WHEEL
spotifio-0.1.6.dist-info/top_level.txt
spotifio-0.1.6.dist-info/RECORD
