Metadata-Version: 2.4
Name: spotifio
Version: 0.1.6
Summary: An async Spotify Web API client library
Home-page: https://github.com/s4w3d0ff/spotifio
Author: s4w3d0ff
Author-email: 
Project-URL: Bug Reports, https://github.com/s4w3d0ff/spotifio/issues
Project-URL: Source, https://github.com/s4w3d0ff/spotifio
Keywords: spotify api async aiohttp music streaming oauth2
Classifier: Development Status :: 3 - Alpha
Classifier: Intended Audience :: Developers
Classifier: License :: OSI Approved :: GNU General Public License v3 (GPLv3)
Classifier: Operating System :: OS Independent
Classifier: Programming Language :: Python :: 3
Classifier: Programming Language :: Python :: 3.7
Classifier: Programming Language :: Python :: 3.8
Classifier: Programming Language :: Python :: 3.9
Classifier: Programming Language :: Python :: 3.10
Classifier: Topic :: Software Development :: Libraries :: Python Modules
Classifier: Framework :: AsyncIO
Requires-Python: >=3.7
License-File: LICENSE
Requires-Dist: aiohttp>=3.8.0
Requires-Dist: aiofiles>=0.8.0
Dynamic: author
Dynamic: classifier
Dynamic: description
Dynamic: description-content-type
Dynamic: home-page
Dynamic: keywords
Dynamic: license-file
Dynamic: project-url
Dynamic: requires-dist
Dynamic: requires-python
Dynamic: summary
